inbreeding/Inbreeding.py
inbreeding/MissingYOB.py
inbreeding/RelationAnimals.py
inbreeding/__init__.py
Inbreeding-0.1.1.3.post11.dist-info/METADATA
Inbreeding-0.1.1.3.post11.dist-info/WHEEL
Inbreeding-0.1.1.3.post11.dist-info/top_level.txt
Inbreeding-0.1.1.3.post11.dist-info/RECORD
