Metadata-Version: 2.1
Name: Inbreeding
Version: 0.1.1.3.post11
Summary: This packages serves as an implementation of the pedigree based inbreeding calculation as proposed by I. Aguilar and I. Misztal in 2008.
Home-page: UNKNOWN
Author: Thomas Rahimi
Author-email: thomas.rahimi@agrar.uni-kassel.de
License: BSD
Platform: UNKNOWN
Classifier: Intended Audience :: Science/Research
Classifier: License :: OSI Approved :: BSD License
Classifier: Operating System :: POSIX :: Linux
Classifier: Programming Language :: Python :: 3
Classifier: Programming Language :: Python :: 3.6
Classifier: Development Status :: 1 - Planning
Requires-Python: >=3.6
Requires-Dist: pandas (>=0.24)
Requires-Dist: numpy (>=1.14)
Requires-Dist: MultiProcessDivision (>=1.0)
